data_manager_metadata/__init__.py
data_manager_metadata/annotation_utils.py
data_manager_metadata/data_tier_api.py
data_manager_metadata/exceptions.py
data_manager_metadata/metadata.py
im_data_manager_metadata-2.1.1.dist-info/LICENSE
im_data_manager_metadata-2.1.1.dist-info/METADATA
im_data_manager_metadata-2.1.1.dist-info/WHEEL
im_data_manager_metadata-2.1.1.dist-info/top_level.txt
im_data_manager_metadata-2.1.1.dist-info/RECORD
