Metadata-Version: 2.1
Name: im-data-manager-metadata
Version: 2.1.1
Summary: A framework for Informatics Matters dataset metadata
Home-page: https://github.com/InformaticsMatters/squonk2-data-manager-metadata
Author: Tim Dudgeon
Author-email: tdudgeon@informaticsmatters.com
License: MIT
Keywords: jenkins
Platform: any
Classifier: Development Status :: 5 - Production/Stable
Classifier: Environment :: Console
Classifier: Intended Audience :: Science/Research
Classifier: License :: OSI Approved :: MIT License
Classifier: Programming Language :: Python :: 3.12
Classifier: Topic :: Software Development :: Libraries :: Python Modules
Requires-Python: >=3, <4
License-File: LICENSE
Requires-Dist: PyYAML <7.0,>=6.0.1
Requires-Dist: im-data-manager-job-decoder <3.0.0,>=2.1.0
